MySQLdb-stubs/METADATA.toml
MySQLdb-stubs/__init__.pyi
MySQLdb-stubs/_exceptions.pyi
MySQLdb-stubs/_mysql.pyi
MySQLdb-stubs/connections.pyi
MySQLdb-stubs/converters.pyi
MySQLdb-stubs/cursors.pyi
MySQLdb-stubs/py.typed
MySQLdb-stubs/release.pyi
MySQLdb-stubs/times.pyi
MySQLdb-stubs/constants/CLIENT.pyi
MySQLdb-stubs/constants/CR.pyi
MySQLdb-stubs/constants/ER.pyi
MySQLdb-stubs/constants/FIELD_TYPE.pyi
MySQLdb-stubs/constants/FLAG.pyi
MySQLdb-stubs/constants/__init__.pyi
types_mysqlclient-2.2.0.20250516.dist-info/licenses/LICENSE
types_mysqlclient-2.2.0.20250516.dist-info/METADATA
types_mysqlclient-2.2.0.20250516.dist-info/WHEEL
types_mysqlclient-2.2.0.20250516.dist-info/top_level.txt
types_mysqlclient-2.2.0.20250516.dist-info/RECORD
